Workbook

Sheet DCF_MODEL
A3: Celulă A | B3: B (2025) | C3: C (2026) | D3: D (2027) | E3: E (2028) | G3: Indicator | H3: 2025 | I3: 2026 | J3: 2027 | K3: 2028 | M3: Indicator | N3: 2025 | O3: 2026 | P3: 2027 | Q3: 2028
A4: 3. Indicator | B4: 2025 | C4: 2026 | D4: 2027 | E4: 2028 | G4: Datorie financiară (mil. lei) | H4: 40 | I4: 40 | J4: 40 | K4: 40 | M4: CAPEX / Venituri | N4: 0.1 | O4: 0.1 | P4: 0.1 | Q4: 0.1
A5: 4. Creștere venituri | B5: — | C5: 0.1 | D5: 0.08 | E5: 0.06 | G5: Rata dobânzii | H5: 0.075 | I5: 0.075 | J5: 0.075 | K5: 0.075 | M5: CAPEX (mil. lei) | N5: =N4*B6 -> 10 | O5: =O4*C6 -> 11 | P5: =P4*D6 -> 11.88 | Q5: =Q4*E6 -> 12.5928
A6: 5. Venituri (mil. lei) | B6: 100 | C6: =B6*(1+C5) -> 110 | D6: =C6*(1+D5) -> 118.8 | E6: =D6*(1+E5) -> 125.928 | G6: Cheltuieli cu dobânzile | H6: =H4*H5 -> 3 | I6: =I4*I5 -> 3 | J6: =J4*J5 -> 3 | K6: =K4*K5 -> 3
A7: 6. Costuri / venituri | B7: 0.7 | C7: 0.7 | D7: 0.7 | E7: 0.7 | G7: Profit înainte de impozitare | H7: =B13-H6 -> 22 | I7: =C13-I6 -> 24.5 | J7: =D13-J6 -> 26.7 | K7: =E13-K6 -> 28.482 | M7: Indicator | N7: 2025 | O7: 2026 | P7: 2027 | Q7: 2028
A8: 7. Costuri operaționale | B8: =B6*B7 -> 70 | C8: =C6*C7 -> 77 | D8: =D6*D7 -> 83.16 | E8: =E6*E7 -> 88.1496 | G8: Cotă impozit pe profit | H8: 0.16 | I8: 0.16 | J8: 0.16 | K8: 0.16 | M8: Creanțe / Venituri | N8: 0.2 | O8: 0.2 | P8: 0.2 | Q8: 0.2
A9: 8. EBITDA | B9: =B6-B8 -> 30 | C9: =C6-C8 -> 33 | D9: =D6-D8 -> 35.64 | E9: =E6-E8 -> 37.7784 | G9: Cheltuială cu impozitul | H9: =H7*H8 -> 3.52 | I9: =I7*I8 -> 3.92 | J9: =J7*J8 -> 4.272 | K9: =K7*K8 -> 4.55712 | M9: Creanțe comerciale | N9: =B6*N8 -> 20 | O9: =C6*O8 -> 22 | P9: =D6*P8 -> 23.76 | Q9: =E6*Q8 -> 25.1856
A10: 9. Marja EBITDA | B10: =B9/B6 -> 0.3 | C10: =C9/C6 -> 0.3 | D10: =D9/D6 -> 0.3 | E10: =E9/E6 -> 0.3 | G10: Profit net | H10: =H7-H9 -> 18.48 | I10: =I7-I9 -> 20.58 | J10: =J7-J9 -> 22.428 | K10: =K7-K9 -> 23.92488 | M10: Creșterea creanțelor | N10: — | O10: =O9-N9 -> 2 | P10: =P9-O9 -> 1.76 | Q10: =Q9-P9 -> 1.4256
A11: Amortizare/venituri | B11: 0.05 | C11: 0.05 | D11: 0.05 | E11: 0.05
A12: Amortizarea | B12: =B6*B11 -> 5 | C12: =C6*C11 -> 5.5 | D12: =D6*D11 -> 5.94 | E12: =E6*E11 -> 6.2964 | G12: Indicator | H12: 2025 | I12: 2026 | J12: 2027 | K12: 2028
A13: EBIT | B13: =B9-B12 -> 25 | C13: =C9-C12 -> 27.5 | D13: =D9-D12 -> 29.7 | E13: =E9-E12 -> 31.482 | G13: Cash Flow Operațional | H13: — | I13: =(I10+C12)-O10 -> 24.08 | J13: =(J10+D12)-P10 -> 26.608 | K13: =(K10+E12)-Q10 -> 28.79568
G14: Free Cash Flow simplificat | H14: — | I14: =I13-O5 -> 13.08 | J14: =J13-P5 -> 14.728 | K14: =K13-Q5 -> 16.20288
A16: Indicator | B16: 2026 | C16: 2027 | D16: 2028 | G16: Indicator | H16: 2026 | I16: 2027 | J16: 2028 | L16: Ipoteză | M16: Valoare | O16: Indicator | P16: Scenariul 1 | Q16: Scenariul 2
A17: EBIT | B17: =C13 -> 27.5 | C17: =D13 -> 29.7 | D17: =E13 -> 31.482 | G17: Anul proiecției | H17: 1 | I17: 2 | J17: 3 | L17: WACC | M17: 0.1 | O17: WACC | P17: 0.1 | Q17: 0.12
A18: Impozit | B18: 0.16 | C18: 0.16 | D18: 0.16 | G18: FCFF | H18: =B23 -> 15.6 | I18: =C23 -> 17.248 | J18: =D23 -> 18.72288 | L18: g | M18: 0.02 | O18: Equity Value (mil. lei) | P18: 191.85 | Q18: 146.94
A19: NOPAT | B19: =C13*(1-I8) -> 23.1 | C19: =D13*(1-J8) -> 24.948 | D19: =E13*(1-K8) -> 26.44488 | G19: Factor de actualizare 10% | H19: =1/(1+$M$17)^H17 -> 0.90909091 | I19: =1/(1+$M$17)^I17 -> 0.82644628 | J19: =1/(1+$M$17)^J17 -> 0.7513148 | L19: Numerar (bilant) | M19: 10 | O19: Preț cerut (mil. lei) | P19: 200 | Q19: 200
A20: + Amortizare | B20: =C12 -> 5.5 | C20: =D12 -> 5.94 | D20: =E12 -> 6.2964 | G20: Valoarea actualizată FCFF 10% | H20: =B23*H19 -> 14.181818 | I20: =C23*I19 -> 14.254545 | J20: =D23*J19 -> 14.066777 | L20: WACC | M20: 0.12 | O20: Diferență valoare − preț | P20: =P18-P19 -> -8.15 | Q20: =Q18-Q19 -> -53.06
A21: − CAPEX | B21: =O5 -> 11 | C21: =P5 -> 11.88 | D21: =Q5 -> 12.5928 | G21: TV2028 | J21: =D23*(1+$M$18)/($M$17-$M$18) -> 238.71672
A22: − Creșterea creanțelor | B22: =O10 -> 2 | C22: =P10 -> 1.76 | D22: =Q10 -> 1.4256 | G22: PV(TV2028 10% | J22: =J21*J19 -> 179.3514 | L22: TV12% | M22: =(D23*(1+M18))/(M20-M18) -> 190.97338
A23: FCFF | B23: =B19+C12-O5-O10 -> 15.6 | C23: =C19+D12-P5-P10 -> 17.248 | D23: =D19+E12-Q5-Q10 -> 18.72288 | G23: EV 10% | J23: =J22+(H20+I20+J20) -> 221.85455 | L23: PV(TV 2028 12% | M23: =M22*J25 -> 135.93108
G24: EQUITI VALUE 10% | J24: =J23-K4+M19 -> 191.85455 | L24: EV 12% | M24: =SUM(H26:J26)+M23 -> 176.93622
G25: Factor de actualizare 12% | H25: =1/(1+$M$20)^H17 -> 0.89285714 | I25: =1/(1+$M$20)^I17 -> 0.79719388 | J25: =1/(1+$M$20)^J17 -> 0.71178025
G26: Valoarea actualizată FCFF 12% | H26: =H18*H25 -> 13.928571 | I26: =I18*I25 -> 13.75 | J26: =J18*J25 -> 13.326576
H27: =J24 -> 191.85455 | I27: 0.01 | J27: 0.02 | K27: 0.03
H28: 0.09 | I28: 195.81264 | J28: 223.95313 | K28: 261.47378
H29: 0.1 | I29: 170.36364 | J29: 191.85455 | K29: 219.48571
H30: 0.11 | I30: 150.01201 | J30: 166.89636 | K30: 188.00179
H31: 0.12 | I31: 133.36735 | J31: 146.93622 | K31: 163.52041

Sheet Valuation_Summary
A1: Scenario | B1: WACC | C1: g | D1: Enterprise Value | E1: Equity Value | F1: Asking Price
A2: base case | B2: 0.1 | C2: 0.02 | D2: =DCF_MODEL!J23 -> 221.85455 | E2: =DCF_MODEL!J24 -> 191.85455 | F2: 200 | H2: Variatie Equiti Value 12%-10% | I2: =E3-Valuation_Summary[[#This Row],[Equity Value]] -> -44.918321
A3: higher risk | B3: 0.12 | C3: 0.02 | D3: =SUM(DCF_MODEL!H26:J26)+DCF_MODEL!M23 -> 176.93622 | E3: =DCF_MODEL!J31 -> 146.93622 | F3: 200 | H3: Variatie(%) Equiti Value 12%/10% | I3: =((Valuation_Summary[[#This Row],[Equity Value]]-E2)/E2) -> -0.23412696
A4: higher growth | B4: 0.1 | C4: 0.03 | D4: =Valuation_Summary[[#This Row],[Equity Value]]+DCF_MODEL!K4-DCF_MODEL!M19 -> 249.48571 | E4: =DCF_MODEL!K29 -> 219.48571 | F4: 200
H5: EV=Equity Value+Datorii-Numerar
J6: Indicator | K6: Formula | L6: Explicație
J7: NOPAT | K7: EBIT*(1-Tax Rate) | L7: Profit operațional după impozit
J8: FCFF | K8: NOPAT+Depreciation-CAPEX-Change in Receivables | L8: Fluxul de numerar disponibil
J9: Present Value | K9: FCFF/(1+WACC)^YEAR | L9: Actualizarea fluxurilor
J10: Terminal Value | K10: FCFF_LastYear*(1+g)/(WACC-g) | L10: Valoarea după perioada de prognoză
J11: Enterprise Value | K11: SUM(PV_FCFF)+PV_TerminalValue | L11: Valoarea operațiunilor companiei
J12: Equity Value | K12: EV-Debt+Cash | L12: Valoarea capitalurilor proprii
J13: Price Gap | K13: EquityValue-AskingPrice | L13: Diferența față de preț
J14: Price Gap % | K14: PriceGap/AskingPrice | L14: Diferența procentuală
J15: Equity Value Change | K15: NewEquityValue-BaseEquityValue | L15: Modificarea între scenarii
J16: Equity Value Change % | K16: (NewEquityValue-BaseEquityValue)/BaseEquityValue | L16: Modificarea procentuală
